netmikro/__init__.py
netmikro/_utils.py
netmikro/connector/__init__.py
netmikro/connector/routeros.py
netmikro/modules/__init__.py
netmikro/modules/validators.py
netmikro-0.1.0.dist-info/LICENSE
netmikro-0.1.0.dist-info/METADATA
netmikro-0.1.0.dist-info/WHEEL
netmikro-0.1.0.dist-info/RECORD
