Metadata-Version: 2.1
Name: netmikro
Version: 0.1.0
Summary: Netmikro is a simple library that provides an easy way to manage Mikrotik routers, simplifying configuration and monitoring tasks.
Author: Henrique Sebastião
Author-email: contato@henriquesebastiao.com
Requires-Python: >=3.11,<4.0
Classifier: Intended Audience :: Information Technology
Classifier: Intended Audience :: System Administrators
Classifier: Intended Audience :: Telecommunications Industry
Classifier: License :: OSI Approved :: MIT License
Classifier: Natural Language :: English
Classifier: Programming Language :: Python :: 3
Classifier: Programming Language :: Python :: 3.11
Classifier: Programming Language :: Python :: 3.12
Classifier: Topic :: System :: Networking
Classifier: Topic :: System :: Networking :: Firewalls
Classifier: Topic :: System :: Networking :: Monitoring :: Hardware Watchdog
Classifier: Topic :: Utilities
Requires-Dist: netmiko (>=4.2.0,<5.0.0)
Project-URL: Bug Tracker, https://github.com/henriquesebastiao/netmikro/issues
Project-URL: Documentation, https://netmikro.henriquesebastiao.com
Project-URL: Homepage, https://netmikro.henriquesebastiao.com
Project-URL: Repository, https://github.com/henriquesebastiao/netmikro
